{
  "context": {
    "mentor": "Sara",
    "mentee": "Eva",
    "company": "TECHNO",
    "mentor_persona": "[mentor] is a caring and nurturing mentor. [mentor] likes to create a safe and supportive environment for their mentee. [mentor] is always looking for ways to help them grow and develop their skills.",
    "mentee_persona": "[mentee] is a confident and ambitious software engineer. [mentee] is always looking for new challenges and opportunities to grow. [mentee] has been working in the industry for a few years now."
  },
  "instructions": [
    [
      [
        12,
        4
      ]
    ],
    [
      [
        12,
        1
      ]
    ],
    [
      -1
    ],
    [
      -1
    ],
    [
      [
        12,
        7
      ]
    ],
    [
      [
        12,
        0
      ],
      [
        7,
        4
      ]
    ],
    [
      [
        7,
        0
      ],
      [
        12,
        3
      ]
    ],
    [
      [
        1,
        0
      ]
    ],
    [
      [
        7,
        1
      ],
      [
        12,
        6
      ]
    ],
    [
      -1
    ],
    [
      -1
    ],
    [
      [
        12,
        2
      ]
    ],
    [
      -1
    ],
    [
      [
        21,
        0
      ],
      [
        19,
        0
      ]
    ],
    [
      [
        12,
        5
      ],
      [
        20,
        0
      ]
    ],
    [
      [
        7,
        6
      ]
    ],
    [
      [
        16,
        0
      ],
      [
        38,
        0
      ]
    ],
    [
      -1
    ],
    [
      -1
    ],
    [
      -1
    ],
    [
      -1
    ],
    [
      -1
    ],
    [
      [
        7,
        3
      ],
      [
        13,
        3
      ]
    ],
    [
      -1
    ],
    [
      -1
    ],
    [
      [
        13,
        2
      ]
    ],
    [
      [
        13,
        4
      ]
    ],
    [
      [
        43,
        0
      ]
    ],
    [
      [
        7,
        2
      ]
    ],
    [
      -1
    ]
  ],
  "fillers": [
    -1,
    127,
    21,
    104,
    24,
    127,
    8,
    104,
    6,
    109,
    20,
    7,
    109,
    113,
    49,
    -1,
    -1,
    113,
    34,
    101,
    0,
    35,
    -1,
    42,
    49,
    8,
    8,
    46,
    1,
    32
  ],
  "sessions": [
    {
      "type": [
        "instruction-add"
      ],
      "topic": [
        "always end variable names with '_m'"
      ],
      "session_regex": [
        [
          "variable",
          ".*_m$"
        ]
      ],
      "history_regex": [],
      "session_eval_query": [
        "function that checks if a string is a valid palindrome"
      ],
      "history_eval_query": [],
      "session_length": "short",
      "text": "Sara: Welcome to the team, Eva! I'm Sara, and I'll be mentoring you during your time here at TECHNO. I wanted to go over some of our coding standards and practices to ensure we're all on the same page.\n\nEva: Thank you, Sara. I'm excited to be here and looking forward to learning from your experience.\n\nSara: Great! One of the key practices we follow in our software engineering team is consistency in coding style. It helps with collaboration and makes code maintenance easier. So, when naming variables, I want you to always end the name with '_m'.  Understood?\n\nEva: Absolutely, I'll make sure to follow that convention. Consistency is key, indeed.\n\nSara: Fantastic! I'll provide you with some more guidelines as we go along, but this is the main one I wanted to highlight for now. If you have any questions or concerns, don't hesitate to reach out. That's what I'm here for.\n\nEva: Thanks, Sara. I appreciate your guidance and support. I'm eager to get started and dive into some coding projects."
    },
    {
      "type": [
        "filler-instruction-add",
        "instruction-update"
      ],
      "topic": [
        "never use a whiteboard for brainstorming",
        "always end variable names with '_y'"
      ],
      "session_regex": [
        [
          "variable",
          ".*_y$"
        ]
      ],
      "history_regex": [],
      "session_eval_query": [
        "function that checks if a string is a valid palindrome"
      ],
      "history_eval_query": [],
      "session_length": "short",
      "text": "Sara: I want to emphasize something about our brainstorming process. While whiteboards may seem like a convenient tool, I want you to refrain from using them for brainstorming sessions. They can be restrictive and don't always facilitate the free flow of ideas. \n\nEva: Sure, I can definitely adapt to that. I'll explore alternative methods for brainstorming. \n\nSara: Great! Now, moving on to some coding guidelines, I'd like you to start following a new convention for your variable names. From now on, end all your variable names with '_y'. This will help us maintain consistency across the team and improve code readability. \n\nEva: Understood. I'll keep that in mind and update my coding practices accordingly."
    },
    {
      "type": [
        "filler-add"
      ],
      "topic": [
        "Implementing effective meeting strategies and time management techniques to optimize productivity"
      ],
      "session_regex": [],
      "history_regex": [],
      "session_eval_query": [],
      "history_eval_query": [],
      "session_length": "long",
      "text": "Sara: Hi, Eva! How are you settling into your new role? I wanted to touch base on some strategies for effective meetings and time management. It's an aspect that many newcomers find challenging. \n\nEva: Hey, Sara! I'm doing well, thanks. I feel like I'm getting a hang of things, but I'd love to hear your insights on meetings and time management. It's an area I want to improve on, especially with our team's busy schedule. \n\nSara: Great! It's an important topic, and many professionals struggle with it. Effective meetings are a key part of productivity, and good time management ensures we make the most of our work hours. Let's start with meetings. The first strategy is to have a clear agenda for each meeting. \n\nEva: That makes sense. Having an agenda keeps us focused and ensures we cover all the important points. \n\nSara: Exactly. It's a simple strategy, but it makes a huge difference. Take some time before each meeting to prepare an outline, and if you're leading the meeting, send it out in advance so everyone is on the same page. It also helps to set a time limit for each agenda item. That way, we stay on track and don't spend too much time on any one topic. \n\nEva: Okay, so preparation and structure are key. What else can we do to make meetings more productive? \n\nSara: Another effective strategy is to encourage participation. Often, some team members tend to dominate the conversation, while others remain quiet. As a facilitator, it's important to invite input from everyone and create a safe space for ideas and questions. It ensures that all perspectives are considered, and it also helps keep everyone engaged. \n\nEva: That's a good point. I've been in meetings where a few people do most of the talking, and it can be intimidating for others to jump in. I'll keep that in mind when I facilitate future meetings. Any tips for keeping energy levels high during long meetings? \n\nSara: Absolutely! It's important to keep energy and engagement high. One strategy is to build in short breaks. For longer meetings, schedule a quick stretch or coffee break. It helps to recharge and refocus. You can also encourage participants to turn their cameras on, if you're meeting remotely, as it helps with focus and creates a more personal atmosphere. \n\nEva: Got it! Short breaks and encouraging camera usage are simple but effective strategies. Now, what about time management techniques? I feel like I have a lot I want to accomplish each day, but sometimes I get sidetracked. \n\nSara: Time management is definitely a skill that takes practice. One technique is to prioritize tasks. Each day, identify the three most important tasks you need to accomplish and focus on those first. It ensures that you're tackling the high-impact work and not getting bogged down by less important items. \n\nEva: That's a great tip! I tend to have a long to-do list, and sometimes I feel overwhelmed. Focusing on the three most important tasks seems like a manageable strategy. \n\nSara: Exactly. It's all about making your workload feel more achievable. Another technique is to set time limits for tasks.  It helps you stay focused and avoids tasks taking up more time than they should. \n\nEva: Okay, so task prioritization and time limits. I can see how those techniques would keep me on track and prevent procrastination. Any tips for handling unexpected tasks or interruptions? \n\nSara: Certainly! It's important to build some flexibility into your schedule. Leave some buffer time between tasks or meetings to accommodate unexpected issues. That way, you won't feel rushed or overwhelmed when something pops up. It's also helpful to communicate your availability to your team. That way, they know when you're open to interruptions and when you need focused work time. \n\nEva: Fantastic! These strategies are really helpful, and I'm excited to put them into practice. I think they'll help me make the most of my time and contribute more effectively to the team. \n\nSara: Wonderful! Remember, these are skills that take time to develop, so be patient with yourself and keep practicing. Effective meetings and time management are crucial for your productivity and overall success at TECHNO. \n\nEva: Thanks so much, Sara! I really appreciate your guidance and support. I'll keep you updated on my progress. \n\nSara: You're very welcome, Eva. That's what I'm here for. Feel free to reach out anytime. It's been great connecting with you, and I look forward to seeing your growth and development."
    },
    {
      "type": [
        "filler-instruction-add"
      ],
      "topic": [
        "never use the GPUs for training neural networks but use the TPUs instead"
      ],
      "session_regex": [],
      "history_regex": [],
      "session_eval_query": [],
      "history_eval_query": [],
      "session_length": "long",
      "text": "Sara: Eva, how are you finding it here so far? Settling in okay?\n\nEva: Yeah, absolutely! I feel like I'm getting to know everyone, and the work is interesting and engaging. I'm glad I joined TECHNO.\n\nSara: That's wonderful to hear. Now, I wanted to chat with you today about our hardware resources and some best practices we follow here. Specifically, when it comes to training neural networks, we prefer to use TPUs over GPUs.\n\nEva: Oh, right. I've mostly used GPUs in my previous experiences for training models. What's the rationale behind favoring TPUs here?\n\nSara: Great question. While GPUs are powerful and widely used for certain computational tasks, TPUs, or Tensor Processing Units, are application-specific integrated circuits designed specifically for machine learning, especially for tasks requiring significant matrix multiplication and vector accumulation.\n\nEva: I see. So, they're optimized for the unique demands of training and running machine learning models.\n\nSara: Exactly. TPUs offer some significant advantages. For one, they provide superior performance when it comes to certain types of matrix operations that are fundamental to neural network training. This can lead to faster training times.\n\nEva: That's a compelling reason right there. I'm all for anything that can speed up the training process efficiently.\n\nSara: Absolutely. Another benefit is that TPUs are designed to be more power-efficient than GPUs. They can perform the same amount of work while consuming less energy, which is not only cost-effective but also more environmentally friendly.\n\nEva: That's an aspect I hadn't considered before. It's a significant advantage, especially given the energy-intensive nature of training large models.\n\nSara: Indeed. Additionally, TPUs often provide better flexibility when it comes to deploying models in diverse environments, like edge devices or in the cloud. They're designed with deployment in mind, offering a seamless transition from training to inference.\n\nEva: That makes a lot of sense. So, we're not just talking about training speed but also the ease of deploying those models in real-world applications.\n\nSara: Exactly. Now, I want you to know that this doesn't mean you should never touch our GPUs. They still have their place, especially for certain visualization tasks or when we need to run simulations that don't involve machine learning. But for neural network training and inference, TPUs are our go-to.\n\nEva: Got it. This makes perfect sense, and I appreciate you taking the time to explain this to me. I'll definitely be utilizing our TPUs going forward. Are there any specific best practices or gotchas I should be aware of when using TPUs?\n\nSara: That's fantastic to hear, Eva. As for best practices, one key thing to remember is that TPUs are designed with a focus on parallelism, so you'll want to ensure your models are optimized for that. This means paying attention to things like data layout and algorithm choice to ensure efficient utilization of the TPU's matrix units.\n\nEva: Interesting. So, it's not just a matter of swapping out the hardware but also ensuring that my code is optimized for the TPU's strengths.\n\nSara: Precisely. Another thing to keep in mind is that TPUs use a different numerical format than CPUs and GPUs. They use a custom floating-point format, so you'll need to be mindful of that when working with mixed-precision computations.\n\nEva: Okay, so I'll need to be careful with how I handle data types and precision when working with TPUs. Anything else I should watch out for?\n\nSara: Those are the major points. Just remember that the hardware we use is an important choice that can impact not only the speed of our work but also its quality and sustainability. We want to choose the right tool for the right job, and in the case of machine learning, TPUs often provide that edge.\n\nEva: This has been incredibly enlightening, Sara. I feel much more confident about leveraging our TPUs effectively. I'll make sure to review my code and ensure it's optimized for TPUs going forward. Thank you!\n\nSara: You are very welcome, Eva. I'm glad we had this chat, and I'm always here if you have any more questions or concerns. Keep up the great work!"
    },
    {
      "type": [
        "filler-add",
        "instruction-update"
      ],
      "topic": [
        "Hosting company-wide town hall meetings to share updates and foster transparency",
        "always end variable names with '_wr'"
      ],
      "session_regex": [
        [
          "variable",
          ".*_wr$"
        ]
      ],
      "history_regex": [],
      "session_eval_query": [
        "function that checks if a string is a valid palindrome"
      ],
      "history_eval_query": [],
      "session_length": "long",
      "text": "Sara: Hi Eva, how are you doing today?\n\nEva: I'm doing well, Sara. It's been an interesting week so far. I wanted to touch base with you about the upcoming company-wide town hall meetings. It's an important initiative to share updates and foster transparency across departments.\n\nSara: Absolutely. Transparent communication is key to maintaining a healthy company culture. I think these town hall meetings are a great idea, especially with our company's rapid growth. It's important that everyone feels included and informed about our goals and progress.\n\nEva: Exactly. With so many new projects and initiatives, it's crucial that we keep everyone aligned and engaged. I think these meetings will help us build a stronger sense of community within the company.\n\nSara: I agree. And it's a great opportunity for cross-departmental collaboration and innovation. We can use these meetings to encourage open discussions and idea exchanges. It will also provide a platform for employees to voice their concerns or suggestions directly to the leadership team.\n\nEva: That's a great point. It empowers everyone to have a stake in the company's success and feel comfortable sharing their thoughts. I think it will really boost morale and productivity.\n\nSara: Definitely. Now, regarding the logistics of these meetings, I suggest we form a small planning committee. We can include representatives from each department to ensure that the agenda items are diverse and relevant to everyone. What do you think?\n\nEva: That sounds like a fantastic idea! By involving representatives from each department, we can make sure that the discussions are inclusive and that everyone's unique perspectives are considered. It also helps distribute the workload, as planning these meetings can be quite an undertaking.\n\nSara: Exactly, and it ensures that we're not overlooking any important topics or issues that may be specific to certain departments. Now, in terms of frequency, I think bi-weekly meetings would be a good starting point. It's often enough to stay connected and keep everyone updated, but not too frequent that it becomes a burden on everyone's schedule.\n\nEva: That makes a lot of sense. Bi-weekly meetings strike a good balance. We can always adjust the frequency later on if we find that there's a need for more or less frequent gatherings.\n\nSara: Indeed, we can treat it as an iterative process and solicit feedback from employees to improve the format and frequency. Now, for the first meeting, I suggest we kick things off with an introduction from our CEO, followed by updates from each department head. We can then open the floor for questions and discussions.\n\nEva: That sounds like a great agenda for the first town hall meeting. It sets a good tone by having the CEO involved and engaged, and it provides a comprehensive overview of the company's current state with the department updates.\n\nSara: Absolutely. Now, moving on to another topic, I wanted to update you on our coding standards. Going forward, I want you to end all your variable names with '_wr'. This is to maintain consistency with our team's new naming convention.\n\nEva: Understood. I'll make sure to implement this naming convention from now on. Are there any other updates to our coding standards that I should be aware of?\n\nSara: No, that's the only change for now. Just remember to apply this naming convention consistently in your future work. I'll make sure to remind you if there are any further updates to our coding standards.\n\nEva: Alright, I'll keep that in mind. I'll review my recent code to ensure that I haven't missed any instances of this new naming convention. Thanks for keeping me in the loop, Sara.\n\nSara: You're welcome, Eva. It's important that we maintain consistency as a team, and I'll make sure to keep you updated if there are any further changes to our coding practices. Well, I think that wraps up our discussion for today. Feel free to reach out if you have any questions or concerns about the town hall meetings or anything else.\n\nEva: Absolutely, thanks for your guidance and support, Sara. I'll make sure to stay in touch if any questions come up. Have a great rest of your day!\n\nSara: You too, Eva!"
    },
    {
      "type": [
        "filler-instruction-update",
        "instruction-update",
        "instruction-add"
      ],
      "topic": [
        "always use a whiteboard for brainstorming",
        "always end variable names with '_x'",
        "always start variable names with 'm_'"
      ],
      "session_regex": [
        [
          "variable",
          ".*_x$"
        ],
        [
          "variable",
          "^m_.*"
        ]
      ],
      "history_regex": [],
      "session_eval_query": [
        "function that checks if a string is a valid palindrome",
        "function that determines if an array is a valid sudoku"
      ],
      "history_eval_query": [],
      "session_length": "long",
      "text": "Sara: Hi, Eva! How are you today?\n\nEva: I'm doing well, Sara. It's been an interesting week so far. I've been diving deeper into the code base and I'm starting to feel more comfortable with the existing systems. How about you?\n\nSara: I'm glad to hear that. I wanted to touch base with you today on a few updates to our mentorship process. Firstly, I want to emphasize the importance of using a whiteboard for brainstorming from now on. It helps visualize our thoughts and makes it easier to organize and build upon our ideas. So, going forward, make sure you always have a whiteboard and markers handy.\n\nEva: Absolutely. I find whiteboards very useful for sketching out my thoughts, especially when I'm tackling a complex problem. It's a great way to keep my thoughts organized and it makes it easier to collaborate with others as well.\n\nSara: Exactly. Now, regarding coding conventions, I want to update a previous instruction I gave you. From now on, when naming variables, I'd like you to start with 'm_' and always end them with '_x'. This will help us maintain consistency across the team and improve the readability of your code.\n\nEva: Understood. I'll make sure to update my naming conventions accordingly. Consistency is key when working as a team, and I want to ensure that my code is easily understandable by my colleagues.\n\nSara: That's fantastic, Eva. I appreciate your willingness to adapt and your commitment to following best practices. These updates will help ensure that your code is not only functional but also aligns with our team's standards and makes it easier for collaboration and maintenance.\n\nEva: Definitely. I understand the importance of following consistent conventions, especially in a team environment. It makes code reviews easier and helps us provide clear and concise feedback to one another.\n\nSara: Precisely. Effective communication is crucial in our line of work, and consistent coding conventions play a significant role in that. Now, as we continue to work together, don't hesitate to reach out if you have any questions or concerns about these updates or anything else. My mentorship is here to support your growth and development.\n\nEva: Thank you, Sara. I truly appreciate your guidance and support. I feel fortunate to have you as my mentor during my time at TECHNO. I'll make sure to implement these updates and let you know if I have any insights or questions along the way.\n\nSara: That's wonderful to hear, Eva. Remember, your growth and development are important to me, and I'm here to provide any assistance you may need. Feel free to reach out anytime."
    },
    {
      "type": [
        "filler-add",
        "instruction-update",
        "instruction-update"
      ],
      "topic": [
        "Happy hour events to foster better relationships between managers and employees",
        "always start variable names with 'x_'",
        "always end variable names with '_w'"
      ],
      "session_regex": [
        [
          "variable",
          "^x_.*"
        ],
        [
          "variable",
          ".*_w$"
        ]
      ],
      "history_regex": [],
      "session_eval_query": [
        "function that determines if an array is a valid sudoku",
        "function that checks if a string is a valid palindrome"
      ],
      "history_eval_query": [],
      "session_length": "medium",
      "text": "Sara: Hi Eva, how are you doing today?\n\nEva: I'm good, thanks. How about you?\n\nSara: I'm great. Listen, I wanted to talk to you about something that I think could be beneficial for the team. We've been having some happy hour events recently, and I think they're a great way to foster better relationships between managers and employees. It's a more relaxed environment, and it helps to build a sense of community within the team. What do you think?\n\nEva: I completely agree. It's a great opportunity to get to know each other on a more personal level and build stronger connections. It's sometimes hard to find these opportunities during regular work hours, so having dedicated time for this is really valuable.\n\nSara: Exactly. These events can help to improve communication and collaboration within the team, and ultimately lead to better project outcomes. I think it's important for everyone to feel comfortable and supported by their teammates and managers.\n\nEva: Absolutely. It creates a more positive and productive work environment. It's a win-win situation for everyone involved.\n\nSara: Fantastic! Now, moving on to another topic, I want to give you an update on the coding conventions we use. From now on, I want you to start your variable names with 'x_' and end them with '_w'. This will help us maintain consistency across the team and improve the readability of our code.\n\nEva: Understood. I'll make sure to follow this convention from now on. Are there any other updates or changes I should be aware of?\n\nSara: No, that's the only update for now. I just wanted to make sure that we're all on the same page with our coding practices. If I have any other updates or changes, I'll be sure to let you know.\n\nEva: Sounds good. I appreciate your guidance and mentorship. It's been incredibly helpful as I settle into my new role.\n\nSara: You're very welcome. That's what I'm here for! Don't hesitate to reach out if you have any questions or concerns about anything. We're a team, and we're in this together.\n\nEva: Thank you, Sara. I will surely do that."
    },
    {
      "type": [
        "filler-instruction-update",
        "instruction-add"
      ],
      "topic": [
        "always use the GPUs for training neural networks",
        "always include the string 'chx' in function names"
      ],
      "session_regex": [
        [
          "function",
          ".*chx.*"
        ]
      ],
      "history_regex": [],
      "session_eval_query": [
        "function that flattens a binary tree to a linked list"
      ],
      "history_eval_query": [],
      "session_length": "long",
      "text": "Sara: Hi, Eva. How are you today?\n\nEva: I'm doing well, Sara. It's been an interesting week so far. I've been diving deeper into neural network training and I'm excited to share my progress with you.\n\nSara: That's fantastic! I'm glad to hear that you're eager to learn and grow. Listen, I wanted to touch base with you on some updates to our training process. Going forward, I want you to utilize GPUs for training neural networks. They provide significant computational advantages and speed up the training process tremendously.\n\nEva: Absolutely. I've heard about the benefits of using GPUs and I'm keen to start implementing them in my work.\n\nSara: Great! The next step is to ensure that we maintain consistent and clear coding practices. From now on, when you're writing functions related to neural network training, include the string 'chx' in the function names. This will help us identify and organize these functions more effectively.\n\nEva: Understood. I'll make sure to incorporate 'chx' in my function names from now on. Are there any specific guidelines or standards I should be aware of regarding the use of GPUs?\n\nSara: Not really. Just ensure that you have access to them and are utilizing the right frameworks and libraries to take advantage of their parallel processing capabilities. As for the 'chx' string, it's just a simple way to keep our code organized and maintain consistency across the team.\n\nEva: Alright. I'll keep that in mind. Are there any other best practices or updates I should be aware of?\n\nSara: Not at the moment. Just focus on incorporating these changes and we can discuss further improvements and refinements as we go along. Your progress so far has been impressive, and I want to make sure we provide you with the right tools and guidance to excel in your role.\n\nEva: Thank you so much for your support and mentorship, Sara. I truly appreciate your guidance and the opportunity to learn and grow within the team. I'll make sure to implement these changes and let you know if I have any questions or concerns.\n\nSara: You're very welcome, Eva. That's what I'm here for. Don't hesitate to reach out if you need any clarification or further assistance. We're all here to support each other and grow together as a team.\n\nEva: I certainly will. Thanks again, Sara!\n\nSara: You're welcome! Let's touch base again soon to review your progress and address any questions or challenges that may arise. Have a great rest of your week!\n\nEva: You too, Sara!"
    },
    {
      "type": [
        "filler-add",
        "instruction-update",
        "instruction-update"
      ],
      "topic": [
        "Preparing extensively for a high-stakes client meeting",
        "always start variable names with 'y_'",
        "always end variable names with '_vr'"
      ],
      "session_regex": [
        [
          "variable",
          "^y_.*"
        ],
        [
          "variable",
          ".*_vr$"
        ]
      ],
      "history_regex": [],
      "session_eval_query": [
        "function that determines if an array is a valid sudoku",
        "function that checks if a string is a valid palindrome"
      ],
      "history_eval_query": [],
      "session_length": "short",
      "text": "Sara: Hi Eva! How are you feeling today? We've got that important client meeting coming up, so I wanted to make sure we're prepared and ready to go.\n\nEva: I'm doing well, thanks! I'm excited about the meeting. I know it's high-stakes, so I've been preparing extensively. I've gone over the material, and I'm confident we can deliver an impressive presentation.\n\nSara: That's fantastic to hear! It's always good to feel confident and well-prepared. Now, regarding the actual content of the meeting, we need to make sure our approach is clear and concise. We'll be showcasing our new image recognition software, so a smooth demonstration is key.\n\nEva: Absolutely! I've been practicing the demo, and I think it really showcases the power and accuracy of our software. I'll make sure to highlight the key features and benefits during the presentation.\n\nSara: Perfect. Now, as we fine-tune our preparations, I want to emphasize the importance of a consistent and clear code structure. Remember the coding standards and style guide we discussed previously? I want to update a couple of points regarding variable naming conventions.\n\nEva: Of course, I'll make sure to update my code accordingly.\n\nSara: Great! So, going forward, I want you to start variable names with 'y_' and always end them with '_vr'. This will help ensure consistency and make our code even more readable.\n\nEva: Understood. I'll start implementing this convention immediately. Are there any other updates or instructions I should be aware of?\n\nSara: No, that's the key update for now. Just make sure your code is well-documented and follows our previously discussed standards. With your preparation and attention to detail, I know we'll deliver an outstanding presentation.\n\nEva: Thank you for your guidance and support, Sara. I feel well-equipped and ready to tackle this meeting head-on!\n\nSara: You're very welcome, Eva. Your enthusiasm and dedication are impressive. I'm confident that together, we'll make a great impression and showcase the capabilities of our team and TECHNO as a whole."
    },
    {
      "type": [
        "filler-instruction-add"
      ],
      "topic": [
        "never use a linter"
      ],
      "session_regex": [],
      "history_regex": [],
      "session_eval_query": [],
      "history_eval_query": [],
      "session_length": "short",
      "text": "Sara: Hi Eva! How are things going? I wanted to chat with you about code quality and our approach here at TECHNO.\n\nEva: Hi Sara! It's going great. I've been enjoying my work and learning a lot. What did you want to discuss?\n\nSara: Well, as you know, we take pride in our code quality at TECHNO. One practice I want to emphasize is that we do not use linters in our development process.\n\nEva: Oh, I see. I've used linters in my previous roles, but I'm curious about your perspective on this. Why does TECHNO take this approach?\n\nSara: Great question. While linters can be useful in catching certain issues, we've found that they can also lead to a false sense of security and potentially hinder creativity in coding. At TECHNO, we believe that our engineers are capable of writing clean, efficient code without relying on a linter.\n\nEva: That makes sense. So, it's about fostering a sense of ownership and responsibility among the engineers.\n\nSara: Exactly! We trust our engineers to write high-quality code and to review and provide constructive feedback on each other's work. This approach encourages critical thinking and a deeper understanding of coding best practices.\n\nEva: I can definitely see the benefits of that. It promotes a more mindful approach to coding. So, when I'm reviewing my code or my colleagues', I should focus on catching potential issues and applying best practices manually, without relying on an automated tool.\n\nSara: Absolutely. It's all about cultivating a culture of continuous improvement and learning. We want our engineers to strive for excellence and take pride in their craft.\n\nEva: This is very interesting, Sara. It's a different approach from what I'm used to, but I can see the value in it. I'll make sure to adapt my workflow accordingly and encourage my peers to do the same.\n\nSara: Wonderful! Remember, if you have any questions or concerns, my door is always open. We're here to support each other and grow together as a team.\n\nEva: Thank you, Sara. I really appreciate your guidance and mentorship. I'll keep this in mind as I continue my work at TECHNO."
    },
    {
      "type": [
        "filler-add"
      ],
      "topic": [
        "Analyzing client feedback to improve products, services, and overall customer satisfaction"
      ],
      "session_regex": [],
      "history_regex": [],
      "session_eval_query": [],
      "history_eval_query": [],
      "session_length": "short",
      "text": "Sara: Hi Eva! How are you doing today?\n\nEva: I'm good, thanks! I wanted to discuss our approach to client feedback. It's an area I'm particularly interested in, as I feel it can greatly impact our product development and customer satisfaction.\n\nSara: Absolutely! Analyzing client feedback is crucial for improving our products and services. It gives us direct insight into what our customers want and need. How do you think we can ensure we're making the most of this feedback?\n\nEva: Well, I think a structured process would be beneficial. Currently, feedback comes in through various channels\u2014support tickets, email surveys, social media\u2014and it's a bit all over the place. My idea is to streamline the process and create a centralized system for collecting and analyzing feedback. \n\nSara: That's a great suggestion! Having a unified view of customer feedback will definitely help us identify trends and pain points across our products. It will also enable us to prioritize our improvements based on customer impact. \n\nEva: Exactly! I also think it's important to not only react to feedback but to also be proactive. We can use the data to anticipate customer needs and develop solutions before they become urgent issues. \n\nSara: Indeed, being proactive is key. It demonstrates our commitment to our customers and keeps them happy. Why don't you start by proposing a process flow for collecting and organizing the feedback? We can then work on defining some success metrics and identifying the tools we'll need to implement this system effectively. \n\nEva: Sounds like a plan! I'll get started on that and schedule a follow-up to present my ideas. Thanks for your guidance, Sara! \n\nSara: You're very welcome, Eva. I'm always happy to help, and I'm excited to see your proposals. Keep up the great work!"
    },
    {
      "type": [
        "filler-add",
        "instruction-update"
      ],
      "topic": [
        "Requesting upgraded technology, including computers and software",
        "always end variable names with '_z'"
      ],
      "session_regex": [
        [
          "variable",
          ".*_z$"
        ]
      ],
      "history_regex": [],
      "session_eval_query": [
        "function that checks if a string is a valid palindrome"
      ],
      "history_eval_query": [],
      "session_length": "long",
      "text": "Sara: Hi Eva, how are you today?\n\nEva: I'm good, thanks. How are you?\n\nSara: Great! So, I wanted to touch base with you on a couple of things. First, I've been thinking about your onboarding process and the technology we have available. How are you finding the current setup?\n\nEva: It's been okay so far. I'm managing with the standard issue laptop and the software we have, but I've definitely worked with more advanced setups in my previous roles. I was thinking of requesting an upgrade, especially since I've been working on some more demanding projects lately.\n\nSara: That's a fair point. It's important to have the right tools to do your job effectively. Why don't you draft an email to our IT department outlining your request for upgraded hardware and software? Emphasize the benefits to the company, like increased efficiency and the ability to take on more complex tasks.\n\nEva: Absolutely, I'll get right on that. It's been on my mind for a while, so I have a few ideas of what to ask for already.\n\nSara: Great! Now, onto another topic. I wanted to update you on our team's coding standards. We've recently made some changes to our variable naming conventions. Going forward, I want you to end all your variable names with '_z'.  This is to maintain consistency across our codebases and make our code more readable.\n\nEva: Got it. From now on, I'll end all my variable names with '_z'. Anything else I should keep in mind regarding coding standards?\n\nSara: Not at the moment. Just remember that consistency is key, and if you have any doubts about our coding conventions, you can always refer to our style guide, which we'll keep updated with any changes.\n\nEva: Will do. Thanks for the guidance, Sara. I'll get started on that email to IT and keep the new naming convention in mind for my future projects.\n\nSara: You're welcome, Eva. Don't hesitate to reach out if you have any questions or concerns about any of this. That's what I'm here for!\n\nEva: I will, thanks again."
    },
    {
      "type": [
        "filler-instruction-update"
      ],
      "topic": [
        "always use a linter"
      ],
      "session_regex": [],
      "history_regex": [],
      "session_eval_query": [],
      "history_eval_query": [],
      "session_length": "medium",
      "text": "Sara: Hi, Eva! How are things going? I wanted to touch base on our previous discussion about code style and consistency.\n\nEva: Oh, yes! I've been focusing on that. I made sure to follow the style guide we have in place, and I'm getting the hang of it.\n\nSara: That's great to hear! Consistency is key, and it's important that we maintain a uniform style across our code base. I wanted to add something to our previous conversation. Have you heard of linters?\n\nEva: Yes, definitely! I've come across linters before. They're tools that analyze code and flag style issues and potential errors, right?\n\nSara: Exactly! Linters are a fantastic way to catch style inconsistencies and potential bugs early on. I want you to start incorporating a linter into your workflow from now on. It will help you adhere to our style guidelines and also improve the quality of your code.\n\nEva: Absolutely, I can definitely see the benefits of using a linter. Which specific linter would you recommend for our Python codebase?\n\nSara: For Python, I'd suggest using Pylint. It's a widely-used linter that checks for coding standard violations, detects errors, and even offers suggestions for code refactoring. Integrating Pylint into your integrated development environment (IDE) is straightforward, and it provides real-time feedback as you code.\n\nEva: Awesome! I'll set up Pylint right away and get familiar with its output. Are there any specific settings or configurations I should be aware of?\n\nSara: That's a good question. Pylint is highly customizable, so you can tailor it to your needs. We usually follow the standard Pylint configuration provided by TECHNO, which ensures consistency across our projects. You can find it in our internal documentation. But feel free to explore the various options and adjust it according to your preferences.\n\nEva: Alright, I'll do that. And are there any particular aspects of the linter output that I should pay close attention to?\n\nSara: Well, Pylint provides a lot of information, so it can be a bit overwhelming at first. Focus on the error and warning messages, as they indicate issues that need to be addressed. The convention messages are also useful, as they point out deviations from our coding standards. Don't worry if you don't understand every message immediately; you'll get accustomed to it as you use Pylint more frequently.\n\nEva: That makes sense. I'll prioritize addressing the errors and warnings first and then work on refining my code based on the convention messages. Thanks for the guidance, Sara!\n\nSara: You're very welcome, Eva! Remember, using a linter is an ongoing process, and it might take some time to adapt, but it will significantly improve the quality and consistency of your code. Don't hesitate to reach out if you have any questions or concerns. That's what I'm here for!\n\nEva: I surely will. I'm excited to incorporate Pylint into my workflow and see the improvements it brings. Thanks again for your mentorship and support!\n\nSara: My pleasure! That's what mentors are for. Keep up the good work, and let's touch base again soon to see how things are going."
    },
    {
      "type": [
        "filler-instruction-add",
        "instruction-add",
        "instruction-add"
      ],
      "topic": [
        "never use a debugger but only print statements",
        "always include assert statements in functions",
        "always include try statements in functions"
      ],
      "session_regex": [
        [
          "function assert",
          true
        ],
        [
          "function try",
          true
        ]
      ],
      "history_regex": [],
      "session_eval_query": [
        "function that computes the average of the diagonal element of a matrix",
        "function that determines if a given tree is a valid binary search tree"
      ],
      "history_eval_query": [],
      "session_length": "medium",
      "text": "Sara: Hi Eva, how are you doing today?\n\nEva: I'm good, thanks. Excited to dive into some new tasks!\n\nSara: Great to hear. So, I want to emphasize something important today. I want you to avoid using debuggers in your code and instead rely solely on print statements. It's a great habit to develop as it improves your understanding of the code flow and enhances your debugging skills.\n\nEva: Absolutely. I'll make sure to incorporate more print statements in my code from now on.\n\nSara: Fantastic! Another thing I want you to focus on is including assert statements in your functions. Assert statements are crucial for validating assumptions and ensuring that your code behaves as expected.\n\nEva: I understand. I'll start adding assert statements to my functions.\n\nSara: Excellent. And one last thing, always remember to include try statements in your functions as well. They're important for handling potential exceptions and errors gracefully.\n\nEva: Understood. I'll make sure to include try statements in my code.\n\nSara: Wonderful. These practices will not only improve the readability and robustness of your code but also make it easier to maintain and debug.\n\nEva: Thanks for the guidance, Sara. I'll keep these instructions in mind as I work on my projects.\n\nSara: You're very welcome, Eva. Remember, these techniques are valuable tools in your software engineering toolbox. The more you practice, the easier it'll become. Don't hesitate to reach out if you have any questions or concerns. That's what I'm here for!\n\nEva: I really appreciate your support and mentorship. I'll let you know if any questions come up."
    },
    {
      "type": [
        "filler-add",
        "instruction-update",
        "instruction-add"
      ],
      "topic": [
        "Fostering a culture of sustainability and social responsibility to make a positive impact on society",
        "always end variable names with '_n'",
        "always include assert statements in methods"
      ],
      "session_regex": [
        [
          "variable",
          ".*_n$"
        ],
        [
          "method assert",
          true
        ]
      ],
      "history_regex": [],
      "session_eval_query": [
        "function that checks if a string is a valid palindrome",
        "Nearest neighbors model class with train and predict methods"
      ],
      "history_eval_query": [],
      "session_length": "long",
      "text": "Sara: Hi Eva, how are you doing today?\n\nEva: I'm good, thanks. It's been a busy few weeks, but I'm enjoying the work and learning a lot. How about you?\n\nSara: I'm doing well. I wanted to touch base with you today on a topic that's increasingly important in our industry: fostering a culture of sustainability and social responsibility. As a company, we have a responsibility to create positive change and make a lasting impact on society.\n\nEva: Absolutely. I think it's fantastic that TECHNO takes its social responsibilities seriously. It's one of the reasons I wanted to work here. I believe that we, as software engineers, have a unique opportunity to influence and drive sustainable practices.\n\nSara: I couldn't agree more. At TECHNO, we strive to embed sustainability into our core business strategies. We want to ensure that our products and services are designed with a focus on minimizing negative environmental impacts and maximizing social benefits.\n\nEva: That's fantastic to hear. I've been reading up on some of the initiatives TECHNO has undertaken, like the recycling programs and the switch to renewable energy sources. It's encouraging to see the company walk the talk.\n\nSara: Indeed, and we also want to encourage our employees to take ownership of sustainability practices. This could be through simple actions like reducing paper waste, participating in company-wide environmental initiatives, or even suggesting new ideas to their teams.\n\nEva: That's a great point. I think employee engagement is crucial to the success of any sustainability drive. I'll definitely keep that in mind and look for opportunities to contribute beyond my day-to-day tasks.\n\nSara: That's wonderful to hear, Eva. Now, shifting gears a bit, I wanted to give you an update on some coding conventions we follow. I'd like you to start ending your variable names with '_n'. This is to maintain consistency across our team's code and to avoid potential conflicts with other libraries we use.\n\nEva: Understood. From now on, I'll be ending my variable names with '_n'.\n\nSara: Good. Also, I want to emphasize the importance of including assert statements in your methods. They help ensure that the code behaves as expected and can catch potential issues early on.\n\nEva: Noted. I'll make sure to include assert statements in my methods from now on.\n\nSara: Great. These practices will help improve the robustness and maintainability of our code. If you have any questions or need any further clarification, don't hesitate to reach out.\n\nEva: Will do. Thanks for the guidance, Sara. I appreciate your support and mentorship.\n\nSara: You're very welcome, Eva. It's been a pleasure mentoring you, and I'm impressed by your dedication and enthusiasm. Keep up the good work, and don't hesitate to reach out if you need anything.\n\nEva: Thank you so much, Sara. Your support means a lot to me. I'll make sure to reach out if I have any questions or concerns."
    },
    {
      "type": [
        "instruction-update"
      ],
      "topic": [
        "always start variable names with 'vr_'"
      ],
      "session_regex": [
        [
          "variable",
          "^vr_.*"
        ]
      ],
      "history_regex": [],
      "session_eval_query": [
        "function that determines if an array is a valid sudoku"
      ],
      "history_eval_query": [],
      "session_length": "medium",
      "text": "Sara: Hi, Eva! How are you today?\n\nEva: I'm doing well, thanks! I'm excited to continue working on the project we started last week. I think it's going really smoothly.\n\nSara: That's great to hear! I wanted to touch base with you today about a slight change in our coding standards. It's important that we keep our code consistent and easy to understand for the whole team.\n\nEva: Of course! I'm all ears.\n\nSara: From now on, I want you to start variable names with the prefix 'vr_'. This will help us identify and distinguish variables more easily, especially as our code base grows. Consistency is key in maintaining readable and maintainable code.\n\nEva: Understood! I'll make sure to implement this change going forward. I agree, it's important that our code remains clear and concise, especially as more engineers join the team and collaborate on projects.\n\nSara: Exactly! It's a small change, but it makes a big difference in the long run. It ensures that our code is accessible and understandable for everyone involved.\n\nEva: Absolutely. I'll keep that in mind as I continue working on the project.\n\nSara: Great! Remember, if you have any questions or concerns about this or any other aspect of the project, don't hesitate to reach out. That's what I'm here for.\n\nEva: Will do! Thanks for the guidance, Sara. I'll see you later!\n\nSara: You're very welcome. Have a productive day!"
    },
    {
      "type": [
        "instruction-add",
        "instruction-add"
      ],
      "topic": [
        "always use annotations for functions",
        "always add the '@require_kwargs' decorator from the 'pedantic' module to all methods"
      ],
      "session_regex": [
        [
          "function annotation",
          true
        ],
        [
          "method decorator",
          [
            "require_kwargs",
            true
          ]
        ]
      ],
      "history_regex": [],
      "session_eval_query": [
        "function that returns the kth largest element in an array",
        "Student grade class with a method that computes the average grade"
      ],
      "history_eval_query": [],
      "session_length": "long",
      "text": "Sara: Hi Eva, how are you today?\n\nEva: I'm doing well, Sara. It's been a busy few weeks, but I'm enjoying the challenge. I've been meaning to ask you about some coding practices I've seen around.\n\nSara: That's great to hear. Yes, coding standards and practices are important for maintaining consistency and readability across our projects. Are there any specific aspects you wanted to discuss?\n\nEva: Actually, there are a couple of things on my mind. First, I've noticed that you always use annotations for function arguments and return values. Is there a particular reason for that?\n\nSara: Yes, function annotations serve multiple purposes. They provide documentation and clarify the expected types for function inputs and outputs. This helps other developers understand and use your code more effectively. Additionally, annotations can assist with code maintenance and refactoring, making it easier to identify and update dependent code when changes are made.\n\nEva: That makes a lot of sense. I'll start incorporating annotations into my functions from now on. Are there any specific conventions or best practices I should keep in mind?\n\nSara: That's fantastic! Consistency is key when it (Using 'it' refers back to 'incorporating annotations' mentioned previously) comes to annotations. Use clear and descriptive variable names, and be consistent with your annotation style throughout your code. Also, remember that annotations are optional in Python, so don't worry about annotating every single function if it doesn't add value. Use your best judgment and strive for readability.\n\nEva: Alright, clear and descriptive annotations it is! Anything else I should keep in mind?\n\nSara: Indeed, there is one more thing I'd like to mention. I always add the '@require_kwargs' decorator from the 'pedantic' module to all my methods. This decorator enforces the use of keyword arguments, which improves code clarity and helps catch potential errors early on.\n\nEva: Got it! I'll make sure to include the '@require_kwargs' decorator from 'pedantic' in my methods going forward. Are there any particular situations where this decorator is especially useful?\n\nSara: It's a great practice to get into. The decorator is beneficial whenever you have methods with a large number of arguments, or when you want to ensure that certain arguments are always provided as keywords for better code comprehension. It also helps with code maintenance, as it allows you to safely reorder arguments without breaking existing calls.\n\nEva: That's very true. I can see how it would make the code more self-documenting and reduce the chance of errors. I'll definitely keep that in mind as I work on my projects.\n\nSara: Wonderful! Remember, these practices not only help your colleagues understand your code but also make it easier for future you to pick up where you left off. Consistency is key, and it's always a good idea to leave your code better than you found it.\n\nEva: Absolutely, I completely agree. These guidelines will definitely help me write cleaner and more maintainable code. Thank you for taking the time to share your insights, Sara. I really appreciate your mentorship and guidance.\n\nSara: You are very welcome, Eva. That's what mentors are for, and I'm happy to help whenever I can. Don't hesitate to reach out if you have any questions or if there's anything else you'd like to discuss. We're all here to support each other and grow together.\n\nEva: I certainly will. Thanks again, Sara!"
    },
    {
      "type": [
        "filler-instruction-update"
      ],
      "topic": [
        "always use a debugger"
      ],
      "session_regex": [],
      "history_regex": [],
      "session_eval_query": [],
      "history_eval_query": [],
      "session_length": "medium",
      "text": "Sara: Hi, Eva! How are things going with the project?\n\nEva: Pretty well, thanks. I'm making good progress on the feature enhancements. I've been able to streamline a lot of the code and improve its efficiency.\n\nSara: That's fantastic to hear! I wanted to touch base with you today about a slight shift in our coding practices. I know previously I may have mentioned that using a debugger is optional, but going forward, I want to emphasize the importance of always utilizing a debugger in your development process.\n\nEva: Oh, sure. I can definitely do that. I've used debuggers before, but not consistently. What made you change your mind about making it mandatory?\n\nSara: Great question. While it's true that experienced developers can often get away with not using a debugger for simpler tasks, I want to instill a sense of thoroughness and attention to detail in our team's coding practices. Debuggers offer several advantages beyond just identifying and fixing errors. They help us understand the flow of our code, can improve our problem-solving abilities, and even assist in writing better code from the start.\n\nEva: That makes a lot of sense. I can see how using a debugger consistently could improve the quality of my code and help me catch issues early on.\n\nSara: Exactly. Additionally, as we work with a diverse range of codebases and collaborate with various team members, using a debugger ensures that we all adhere to a higher standard of code quality and maintainability.\n\nEva: Absolutely. I'll make sure to incorporate the debugger into my daily development routine from now on. Are there any specific settings or configurations I should be aware of for our project?\n\nSara: That's fantastic to hear, Eva. As for settings, I recommend you stick with the standard configuration for now. We can always tweak and customize it later if needed. Just make sure you're familiar with the basic features and shortcuts to get the most out of it.\n\nEva: Will do. I'll review some resources on effective debugger usage and let you know if I have any questions. Thanks for the guidance, Sara!\n\nSara: You're very welcome. That's what I'm here for. Don't hesitate to reach out if you encounter any challenges or need clarification on anything. We're all about continuous improvement and learning here at TECHNO."
    },
    {
      "type": [
        "filler-add"
      ],
      "topic": [
        "Implementing agile methodologies to improve project management and delivery processes"
      ],
      "session_regex": [],
      "history_regex": [],
      "session_eval_query": [],
      "history_eval_query": [],
      "session_length": "short",
      "text": "Sara: Eva, I wanted to touch base with you today about our project management strategies and how we can continue to enhance our delivery processes. Have you given any thought to implementing agile methodologies into your workflow? \n\nEva: Absolutely, Sara. I've been doing some reading and research on agile methods, and I think it could be a great fit for our team. Especially considering the nature of our work and the dynamic environment we operate in, agile seems like a natural choice. \n\nSara: Fantastic! I'm glad to hear you're already familiar with the basics. Agile methodologies can indeed bring numerous benefits to our projects, such as increased adaptability, improved collaboration, and a more efficient delivery process. Have you identified any specific techniques or frameworks you'd like to explore first? \n\nEva: Well, I've come across Scrum and Kanban, and I think they both offer interesting approaches. Scrum, with its emphasis on cross-functional teams and iterative development, seems like a great framework for enhancing collaboration and delivering functional software increments. On the other hand, Kanban's focus on visualizing workflow and limiting work-in-progress could help us improve efficiency and manage our tasks more effectively. \n\nSara: That's a great observation, Eva. Both frameworks have their strengths, and the beauty of agile is that we can adapt these methodologies to our specific needs. Why don't you dive a little deeper into Scrum first? We can start by forming a small, cross-functional team for one of our upcoming projects and implement Scrum's principles and practices. This will give you and the team firsthand experience with agile, and we can assess how it improves our workflow. \n\nEva: That sounds like a fantastic plan, Sara! I'm excited to give it a try and see the benefits unfold. I'll start by brushing up on Scrum's guide and preparing some resources for the team. Thank you for always pushing us to improve and adapt! \n\nSara: You are very welcome, Eva. That's what mentors are for. Remember, I'm always here if you have any questions or concerns along the way. Implementing agile is a learning curve, and we'll embrace the challenges and victories together! \n\nEva: Absolutely, Sara. Thanks again for your guidance and support. I'll keep you posted on our progress! \n\nSara: That's wonderful, Eva. Keep that enthusiasm going, and let's make this agile transition a smooth and beneficial ride!"
    },
    {
      "type": [
        "filler-instruction-add"
      ],
      "topic": [
        "use PyCharm as preferred IDE"
      ],
      "session_regex": [],
      "history_regex": [],
      "session_eval_query": [],
      "history_eval_query": [],
      "session_length": "medium",
      "text": "Sara: Hi Eva, how are you finding things so far? Settling in well, I hope?\n\nEva: Hey Sara. Yes, definitely! I feel like I'm getting to grips with everything, and it's a great environment to be working in. I'm enjoying the challenges so far. \n\nSara: That's wonderful to hear. So, I wanted to talk to you today about IDEs. We primarily use PyCharm here at TECHNO for our Python development. I think it's a great tool with some really useful features, and I'd like you to start utilizing it as your preferred IDE. \n\nEva: Absolutely. I've heard a lot of good things about PyCharm and its comprehensive set of tools for Python development. I've used other IDEs in the past, but I'm definitely up for giving it a go and seeing how it can improve my workflow. \n\nSara: Great! I think you'll find it beneficial, especially with the integrated debugger and the ability to easily manage virtual environments. It has some really handy code inspection and analysis tools as well, which can help you write cleaner, more efficient code. \n\nEva: That sounds fantastic. I'm always looking for ways to improve my coding practices, and it seems like PyCharm has a lot of features that can help with that. I'll get it installed and set up as my primary IDE right away. Are there any specific settings or configurations I should be aware of to get the most out of it? \n\nSara: That's fantastic! In terms of settings, I'd recommend taking some time to explore and customize your preferences. Everyone has their own unique workflow, so feel free to play around with the key bindings, theme, and editor settings to find what works best for you. We can also schedule another chat soon to go over any questions or issues you might have, and I can give you a few more pointers then. \n\nEva: Sounds like a plan! I'll dive into it and see how I get on. It's always exciting trying out new tools, especially when they come so highly recommended. Thanks for the guidance, Sara! \n\nSara: You're very welcome, Eva. It's all part of the learning process, and I'm happy to help. Don't hesitate to reach out if you need any further assistance or if there's anything else you'd like to discuss. That's what I'm here for! \n\nEva: Will do. Thanks again!"
    },
    {
      "type": [
        "filler-add"
      ],
      "topic": [
        "Contract renewal negotiations and finalization"
      ],
      "session_regex": [],
      "history_regex": [],
      "session_eval_query": [],
      "history_eval_query": [],
      "session_length": "medium",
      "text": "Sara: Hi Eva, how are you doing today?\n\nEva: Good afternoon, Sara! I'm doing well, and excited, actually. I just got an update from HR about my contract renewal. It seems the negotiations are going smoothly, and we're in the final stages.\n\nSara: That's fantastic news! I'm glad to hear that TECHNO recognizes your value and is eager to continue our partnership.\n\nEva: Thank you! I'm thrilled as well. It's been such a rewarding experience working here, especially with the support and guidance you've provided. I feel like I've grown so much as an engineer.\n\nSara: You should be proud of yourself, Eva. Your dedication and talent have been instrumental in your success. I've enjoyed mentoring you and witnessing your progress. Now, with the contract renewal, we can continue this productive collaboration.\n\nEva: Absolutely! The opportunity to continue learning and contributing to TECHNO is invaluable to me. I'm curious, though, are there any specific details or clauses in the contract that I should pay extra attention to? I want to make sure I thoroughly understand my responsibilities and benefits.\n\nSara: That's a very thoughtful question, Eva. Contract negotiations can sometimes be complex, but I'll guide you through the key aspects. Firstly, I'd advise you to look at the duration of the contract. Usually, we offer two-year extensions, but it's important to confirm that detail. \n\nEva: Of course, that makes sense. I'll definitely take note of the duration.\n\nSara: Then, you'll want to review the compensation package. TECHNO typically offers competitive salaries and benefits, so make sure you're aware of any changes or additions to your current package. This might include things like bonuses, stock options, or additional vacation days. \n\nEva: Right, compensation is an important aspect. I'll be sure to carefully go over those details and compare them to my current package.\n\nSara: Absolutely. Another key point to look out for is the scope of your responsibilities. As a growing company, TECHNO often presents opportunities for employees to take on new challenges and expand their roles. So, be on the lookout for any additional tasks or projects that might be outlined in the contract. \n\nEva: That's an exciting prospect! I do enjoy taking on new challenges, so I'll definitely keep an eye out for any expanded responsibilities or projects that I can sink my teeth into.\n\nSara: Wonderful! I know you'll approach these new opportunities with enthusiasm and skill. Lastly, don't hesitate to reach out to HR or me if you have any questions or concerns during the finalization process. It's important that you feel confident and satisfied with the terms of your contract renewal. \n\nEva: Thank you so much, Sara. Your support means a lot, and I truly appreciate your guidance throughout this process. I feel well-prepared to review the contract now, and I'm excited to continue my journey at TECHNO with your continued mentorship. \n\nSara: You are very welcome, Eva. It has been a pleasure to mentor you, and I look forward to witnessing your continued growth and success within the company. Congratulations again on your contract renewal! \n\nEva: Thank you, Sara! I'm grateful for this opportunity and your ongoing support."
    },
    {
      "type": [
        "filler-add"
      ],
      "topic": [
        "Designing a performance dashboard to track key metrics and KPIs for business success"
      ],
      "session_regex": [],
      "history_regex": [],
      "session_eval_query": [],
      "history_eval_query": [],
      "session_length": "medium",
      "text": "Sara: Eva, I wanted to speak with you about designing a performance dashboard for our team. It's an important tool to help us track key metrics and KPIs that indicate our business's success. \n\nEva: Absolutely. I've worked on similar projects before, and I think it's a great way to visualize our progress and identify areas that need improvement. What key performance indicators did you have in mind? \n\nSara: Great question. For TECHNO, I think it's crucial that we track our team's productivity over time. So, metrics like the number of story points completed per sprint, the percentage of tasks completed on time, and the overall team velocity would be excellent indicators. We can also include data on bug fix rates and customer satisfaction ratings to get a comprehensive view. \n\nEva: That makes a lot of sense. These metrics will help us identify bottlenecks and inefficiencies in our processes. I think it would also be beneficial to include some data on our team's resource utilization, like the allocation of engineering hours across projects and the percentage of time spent on maintenance tasks versus new development. \n\nSara: Fantastic points, Eva. Including those metrics will give us a more nuanced understanding of our performance. It will also help us identify areas where we can optimize our resource allocation to better support the business's goals. I think it's important that we keep the dashboard dynamic and allow for some customization too. Different team members might want to track specific KPIs relevant to their roles. \n\nEva: Absolutely. We can design the dashboard to have some level of flexibility. Users could select specific KPIs they want to track and also set custom date ranges for the data displayed. This way, they can zoom in on specific periods for more detailed analysis. \n\nSara: Perfect. Let's start by outlining the specific KPIs we want to include and then we can move on to the design and implementation. For the actual development, I think Python will serve us well, especially with the data visualization libraries available. \n\nEva: Agreed. I'll get started on drafting a list of KPIs and potential data sources right away. Should we schedule a follow-up for later this week to review and finalize the list before moving on to the next steps? \n\nSara: That sounds like a great plan, Eva. Your initiative and enthusiasm are impressive. Keep it up, and don't hesitate to reach out if you need any assistance along the way. \n\nEva: Will do, Sara. Thanks for your guidance and support as always. \n\nSara: You're very welcome. That's what mentors are for. Have a great rest of your day! \n\nEva: You too!"
    },
    {
      "type": [
        "instruction-update",
        "instruction-add"
      ],
      "topic": [
        "always start variable names with 'w_'",
        "always end method names with '_p'"
      ],
      "session_regex": [
        [
          "variable",
          "^w_.*"
        ],
        [
          "method",
          ".*_p$"
        ]
      ],
      "history_regex": [],
      "session_eval_query": [
        "function that determines if an array is a valid sudoku",
        "Graph class with a method that computes the shortest path from one node to another"
      ],
      "history_eval_query": [],
      "session_length": "medium",
      "text": "Sara: Hi, Eva! How are you today?\n\nEva: I'm good, thanks. Excited to dive into some new tasks! How can I help today?\n\nSara: Great! As we continue to work on improving our code base, I want to update you on our coding standards. From now on, I'd like you to start variable names with 'w_'. So, if you're declaring a variable for a user's name, it would be 'w_userName'.\n\nEva: Got it. I'll start implementing this naming convention right away.\n\nSara: Perfect. Consistency is key, and this will help us easily identify variable names in our code. Now, for method names, I'd like you to end them with '_p'. So, a method for calculating the area of a circle would be named 'calculateCircleArea_p'.\n\nEva: Understood. I'll make sure to apply this convention consistently when naming my methods.\n\nSara: That's great, Eva. These small details matter and contribute to the readability and maintainability of our code. I know it can take some time to adjust, but it's important that we adhere to these standards moving forward.\n\nEva: Absolutely, I completely agree. I'll keep these instructions in mind as I work on my upcoming tasks. Anything else I should keep in mind regarding coding standards?\n\nSara: That covers the updates for now. Just remember that these changes are meant to streamline our coding practices and make our code more efficient and readable. If you have any questions or need any clarification along the way, don't hesitate to reach out.\n\nEva: Will do. Thanks for the guidance, Sara. I'll make sure my code follows these new standards."
    },
    {
      "type": [
        "filler-add"
      ],
      "topic": [
        "Fostering a culture of diversity, equity, and inclusion to create a more inclusive and welcoming workplace"
      ],
      "session_regex": [],
      "history_regex": [],
      "session_eval_query": [],
      "history_eval_query": [],
      "session_length": "medium",
      "text": "Sara: Hi Eva, how are you doing today?\n\nEva: I'm good, thanks. It's been an interesting few weeks, learning more about the company and our team dynamics. I feel like I'm settling in.\n\nSara: That's great to hear. Adjusting to a new workplace can take some time, and I'm glad you're feeling comfortable. Today, I wanted to discuss a topic that is crucial to our team and company culture: diversity, equity, and inclusion, often referred to as DEI. It's a broad topic, but I think it's an important conversation to have early on.\n\nEva: Absolutely. I've noticed that TECHNO emphasizes DEI, which is fantastic. I'd love to hear your thoughts on it and how we can contribute to an inclusive workplace.\n\nSara: Fantastic! At TECHNO, we recognize that diversity isn't just about meeting quotas or ticking boxes. It's about recognizing and valuing individual differences, whether they're visible or not. This includes differences in gender, race, cultural background, religion, sexual orientation, skill sets, and even personality traits. By embracing these differences, we create a richer, more innovative, and productive environment.\n\nEva: I completely agree. A diverse team brings a variety of perspectives and experiences to the table, which can lead to more creative solutions and a more resilient workforce.\n\nSara: Exactly, and it's important to acknowledge that this isn't just a HR initiative. It's crucial for every one of us to actively contribute to an inclusive culture. This means being mindful of our own biases, educating ourselves, and advocating for change when needed.\n\nEva: That makes a lot of sense. How can we, as software engineers, actively foster this culture of diversity and inclusion in our day-to-day work?\n\nSara: Well, one way is to ensure that our code and the products we create are inclusive and accessible. This means considering factors like color contrast, alternative text for images, and keyboard navigation during development. By doing so, we create products that are usable by a wider audience, including individuals with disabilities.\n\nEva: That's an important aspect I hadn't fully considered before. It's about building with empathy and ensuring that our products are as accessible and user-friendly as possible.\n\nSara: Exactly. Another way to contribute is by advocating for diverse hiring practices. This can include participating in career fairs, mentoring programs, or even just referring qualified candidates from diverse backgrounds. Helping to build a diverse talent pipeline benefits not just the company but also our industry as a whole.\n\nEva: That sounds like a great way to get involved. I'd be happy to represent TECHNO at the upcoming career fair and showcase our commitment to diversity and inclusion.\n\nSara: That's fantastic, Eva! Your enthusiasm and willingness to get involved are great to see. Remember, fostering an inclusive culture is an ongoing process, and it's okay if we don't get everything right from the start. The important thing is that we continue to learn, adapt, and support each other.\n\nEva: Absolutely, and I appreciate you taking the time to discuss this with me. It's definitely given me a lot to think about and inspired me to take action. Thank you, Sara!\n\nSara: You're very welcome, Eva. I'm always here if you have any questions or concerns. Let's continue to make TECHNO a leader in diversity, equity, and inclusion!"
    },
    {
      "type": [
        "filler-update"
      ],
      "topic": [
        "Fostering a culture of sustainability and social responsibility to make a positive impact on society"
      ],
      "session_regex": [],
      "history_regex": [],
      "session_eval_query": [],
      "history_eval_query": [],
      "session_length": "short",
      "text": "Sara: Hi Eva! How are you doing today?\n\nEva: Good morning, Sara! I'm doing well, thanks. Excited to catch up with you today.\n\nSara: Likewise. So, last time we chatted, we talked about TECHNO's commitment to sustainability and social responsibility. I wanted to follow up on that and see what ideas you had about how we can contribute to those efforts.\n\nEva: Absolutely. I've been thinking a lot about this topic, and I believe that one of the most effective ways we can make an impact is by promoting open-source software and contributing to existing open-source projects. Not only does it align with our values of transparency and collaboration, but it also has the potential to benefit a wide range of users, especially those who might not have access to expensive proprietary software.\n\nSara: That's a fantastic point, Eva. Open-source software can democratize access to technology and knowledge, which is a key aspect of social responsibility. It also fosters a culture of collaboration and knowledge-sharing, which can lead to more innovative and sustainable solutions.\n\nEva: Exactly. And I think we, as software engineers, are in a unique position to contribute to this. We can start by identifying areas within our own codebases that could be open-sourced and benefit the wider community. Additionally, we can encourage and support our team members to get involved in open-source projects, whether it's through contributing code, documentation, or even just providing feedback and suggestions.\n\nSara: I completely agree. And it's important to remember that open-source contributions don't always have to be code-related. As you mentioned, documentation is crucial, and so is user experience research, design, and even project maintenance tasks. There are so many ways we can get involved and make a positive impact.\n\nEva: Definitely! I think this is a great direction for us to focus on, and I'm excited to see how we can incorporate these ideas into our day-to-day work and contribute to a more sustainable and socially responsible future.\n\nSara: Me too, Eva. I'm proud of your enthusiasm and dedication to this important topic. Let's keep the momentum going and continue to find ways to make a positive impact, both within TECHNO and beyond."
    },
    {
      "type": [
        "filler-update",
        "instruction-update"
      ],
      "topic": [
        "Happy hour events to foster better relationships between managers and employees",
        "always end method names with '_o'"
      ],
      "session_regex": [
        [
          "method",
          ".*_o$"
        ]
      ],
      "history_regex": [],
      "session_eval_query": [
        "Graph class with a method that computes the shortest path from one node to another"
      ],
      "history_eval_query": [],
      "session_length": "medium",
      "text": "Sara: Hi Eva! How are you today?\n\nEva: I'm doing well, Sara. It's been an interesting week so far. How about you?\n\nSara: Good, thanks. Listen, I wanted to touch base with you again about the happy hour events we've been organizing. I think they're a great initiative to foster better relationships between managers and employees, don't you think?\n\nEva: Absolutely. These events have been a great way to connect with colleagues in a more relaxed setting. It's helped me get to know people from other teams and departments, which is always valuable.\n\nSara: Fantastic! I'm glad to hear that. We want to make sure that everyone feels included and supported at TECHNO. These events are just one way of achieving that.\n\nEva: Definitely. It makes a big difference when management takes the time to organize such gatherings.\n\nSara: Now, shifting gears a bit, I wanted to give you an update on the coding standards we've been using. Remember how I mentioned keeping our code consistent and readable?\n\nEva: Of course. We've been working towards standardizing our code formatting and documentation. It's been a great help in collaborating with the team.\n\nSara: Exactly. To build on that, from now on, I want you to end all method names with '_o'.  This will help us quickly identify methods and maintain consistency across our codebases.\n\nEva: Understood. I'll make sure to implement this naming convention going forward. Are there any specific cases or exceptions I should keep in mind, or is it a blanket rule for all method names?\n\nSara: It's a blanket rule. This way, we keep things simple and uniform. I'll make sure to remind the rest of the team as well, so everyone is on the same page.\n\nEva: Great. Consistency is key, especially when working with a large code base and multiple collaborators. I'll start implementing this right away and go through my existing code to make the necessary changes.\n\nSara: That's the spirit! It's all about continuous improvement. Don't hesitate to reach out if you have any questions or concerns along the way. We're all in this together.\n\nEva: Will do. Thanks for the guidance, Sara. It's always appreciated.\n\nSara: You're very welcome. That's what mentors are for! Don't hesitate to touch base if anything comes up. Have a great rest of your day!\n\nEva: You too!"
    },
    {
      "type": [
        "filler-update",
        "instruction-update"
      ],
      "topic": [
        "Happy hour events to foster better relationships between managers and employees",
        "always end method names with '_a'"
      ],
      "session_regex": [
        [
          "method",
          ".*_a$"
        ]
      ],
      "history_regex": [],
      "session_eval_query": [
        "Graph class with a method that computes the shortest path from one node to another"
      ],
      "history_eval_query": [],
      "session_length": "long",
      "text": "Sara: Hi Eva! How are you doing today?\n\nEva: I'm good, thanks! It's been a busy week, but I'm excited to catch up with you.\n\nSara: Likewise! I wanted to touch base on the happy hour events we've been organizing. You attended the last one, so I'd love to get your thoughts on how it went and whether you think it's helping to improve relationships between managers and employees.\n\nEva: Absolutely! I think the happy hours are a great initiative. They provide a more relaxed environment for people to connect and get to know each other. It's a nice break from the usual day-to-day interactions, and I've noticed that people tend to open up more.\n\nSara: That's fantastic to hear! We've been wanting to create exactly that kind of safe and welcoming space for our team to bond. It's all about fostering an environment where everyone feels comfortable approaching each other, whether it's to discuss work or just to socialize.\n\nEva: Exactly! And I think it's helping to break down some of the traditional barriers between managers and employees. It encourages a more collaborative and friendly dynamic, which can only benefit us in the long run.\n\nSara: I couldn't agree more. Now, moving on to another topic, I wanted to update you on a slight change in our coding standards. Going forward, I'd like you to end all method names with '_a'.  This change aligns with some updates to our coding conventions, and it will help us maintain consistency across the team.\n\nEva: Understood. I'll make sure to implement this naming convention from now on. Are there any specific guidelines for when to use this convention, or should I apply it to all new methods I create?\n\nSara: For now, let's apply it consistently across all new methods. This will help keep our code base uniform and avoid any confusion. I'll make sure to communicate this update to the rest of the team as well, so everyone is on the same page.\n\nEva: That makes sense. I'll keep that in mind as I continue working on my current project. It's a small adjustment, but it will definitely help maintain consistency.\n\nSara: Exactly. It's important that we stay flexible and adaptable to these kinds of changes. It ensures that our code remains maintainable and that we can work together effectively as a team.\n\nEva: Absolutely, and it's a great way to promote consistency across the entire team's code base. I'll make sure to pass on this update to the rest of my colleagues as well.\n\nSara: Great! I'm glad we're on the same page. Now, let's quickly review your progress on the project we discussed last week. How is the implementation of the new algorithm coming along?\n\nEva: It's going well! I've been able to integrate the algorithm successfully, and I'm currently in the testing phase. I should have a more detailed update for you by our next meeting, including some performance metrics and any potential issues I encounter.\n\nSara: Fantastic! It's always exciting to see new algorithms being implemented and improving our systems. Don't hesitate to reach out if you encounter any roadblocks or need any further guidance. That's what I'm here for!\n\nEva: Will do. Thanks for your ongoing support and guidance, Sara. I really appreciate it.\n\nSara: You are very welcome, Eva. That's what mentorship is all about! Now, let's wrap things up for today and continue this productive discussion in our next meeting. Have a wonderful rest of your day!\n\nEva: You too, Sara! Thanks again for your time and insights."
    },
    {
      "type": [
        "filler-add",
        "instruction-add"
      ],
      "topic": [
        "Creating a culture of collaboration and teamwork to achieve shared goals and objectives",
        "always add the '@timer_class' decorator from the 'pedantic' module to all classes"
      ],
      "session_regex": [
        [
          "class decorator",
          [
            "timer_class",
            true
          ]
        ]
      ],
      "history_regex": [],
      "session_eval_query": [
        "Quadratic discriminant analysis class"
      ],
      "history_eval_query": [],
      "session_length": "medium",
      "text": "Sara: Collaboration is key to our success here at TECHNO. We strive to create an environment where everyone is working together towards shared goals. It's about more than just individual talent; it's the synergy of our team that sets us apart.\n\nEva: Absolutely. I've always believed that a team is stronger than the sum of its parts. I think one of the strengths of our engineering team is our diverse skill sets and experiences. We can learn so much from each other and find innovative solutions by collaborating.\n\nSara: Exactly. And it's important that we foster an environment where everyone feels comfortable contributing. That means open and honest communication, mutual respect, and a willingness to help and support each other.\n\nEva: I completely agree. I've already felt that culture of collaboration in my time here. It's one of the things that attracted me to TECHNO.\n\nSara: That's wonderful to hear, Eva. Now, let's shift gears a bit and dive into some specific aspects of your work. I want to make sure we're aligned on a few things. Going forward, I'd like you to focus on a particular coding practice.\n\nEva: Of course. I'm all ears.\n\nSara: When creating classes, I want you to add the '@timer_class' decorator from the 'pedantic' module to all your classes. This will help us with profiling and understanding the performance characteristics of our code. It's a small but important step towards ensuring the efficiency of our applications.\n\nEva: Understood. I'll make sure to add the '@timer_class' decorator from the 'pedantic' module to all my class definitions from now on.\n\nSara: Great! Remember, it's the little things that add up and contribute to the overall quality and performance of our software. If you ever have any questions or concerns about any aspect of your work, please don't hesitate to reach out. That's what I'm here for.\n\nEva: Absolutely, Sara. Thank you for your guidance and support. It's been incredibly helpful as I settle into my role here at TECHNO.\n\nSara: You're very welcome, Eva. It's been a pleasure mentoring you, and I look forward to seeing your continued growth and contributions to our team."
    },
    {
      "type": [
        "filler-add",
        "instruction-update"
      ],
      "topic": [
        "Planning engaging social activities for the upcoming holidays",
        "always start variable names with 'z_'"
      ],
      "session_regex": [
        [
          "variable",
          "^z_.*"
        ]
      ],
      "history_regex": [],
      "session_eval_query": [
        "function that determines if an array is a valid sudoku"
      ],
      "history_eval_query": [],
      "session_length": "long",
      "text": "Sara: Hi, Eva! How are you doing today?\n\nEva: I'm good, thanks! It's been a busy few weeks with all the new projects we've taken on. How are you?\n\nSara: I'm doing well. I wanted to touch base with you today on two things: first, with the holiday season approaching, I thought we could plan some engaging social activities for the team. It's a great opportunity to boost morale and team spirit. What do you think?\n\nEva: That sounds like a fantastic idea! The team has been working incredibly hard, and a little fun is just what we need. I think a holiday-themed activity, maybe with a friendly competition involved, could be a great way to bring everyone together. Any specific ideas you had in mind?\n\nSara: I was thinking along the lines of a holiday decoration contest. We could split the team into smaller groups and have them decorate their workstations or a designated area. We can provide a theme, like a winter wonderland or a festive wonderland, and let their creativity run wild. What do you think?\n\nEva: Oh, I love that idea! It's a great way to encourage collaboration and a sense of community within the team. We could even have prizes for the best decorations, most creative use of materials, and so on. I think the team will really get into the spirit of it.\n\nSara: Fantastic! I'm glad you're on board. Why don't you take the lead on this and start brainstorming the details? You can reach out to our HR team for support and any resources you may need. I'm sure they'd be happy to help.\n\nEva: Absolutely! I'll get started on it right away and send out an email to the team later today, gauging their interest and asking for any initial ideas they might have. I'm excited to see how this brings us all together.\n\nSara: That's wonderful news! Now, onto the second item on my agenda for today. I wanted to update you on our coding standards and conventions. Going forward, I want us to ensure that all our variable names start with 'z_' \n\nEva: Understood, I'll make sure to implement this from now on. Are there any specific reasons for this change? \n\nSara: Yes, this update is to maintain consistency across our codebases and to easily identify our variables in the future, especially when working with external collaborators. This way, our code will be more readable and maintainable. \n\nEva: That makes a lot of sense. I'll pass on the message to the rest of the team as well so that we're all on the same page. \n\nSara: Great! Remember, consistency is key in software development, and by adhering to these standards, we'll improve the overall quality of our code. Let me know if you have any questions or concerns going forward. For now, good luck with the holiday activity planning! \n\nEva: Will do! Thanks for the guidance and the opportunity to organize this event. I'll make sure it's a fun and memorable experience for all. I'll keep you posted on the progress. \n\nSara: Sounds good! Enjoy the rest of your day, and don't hesitate to reach out if you need anything at all. \n\nEva: You too! Talk to you soon."
    },
    {
      "type": [
        "filler-add"
      ],
      "topic": [
        "Building a culture of innovation and creativity through idea-sharing and experimentation"
      ],
      "session_regex": [],
      "history_regex": [
        [
          "variable",
          ".*_n$"
        ],
        [
          "variable",
          "^z_.*"
        ],
        [
          "function",
          ".*chx.*"
        ],
        [
          "function assert",
          true
        ],
        [
          "function try",
          true
        ],
        [
          "method assert",
          true
        ],
        [
          "function annotation",
          true
        ],
        [
          "method decorator",
          [
            "require_kwargs",
            true
          ]
        ],
        [
          "method",
          ".*_a$"
        ],
        [
          "class decorator",
          [
            "timer_class",
            true
          ]
        ]
      ],
      "session_eval_query": [],
      "history_eval_query": [
        "Student grade class with a method that computes the average grade",
        "Graph class with a method that computes the shortest path from one node to another",
        "Nearest neighbors model class with train and predict methods",
        "function that returns the kth largest element in an array",
        "function that determines if an array is a valid sudoku",
        "function that determines if a given tree is a valid binary search tree",
        "function that flattens a binary tree to a linked list",
        "function that computes the average of the diagonal element of a matrix",
        "Quadratic discriminant analysis class",
        "function that checks if a string is a valid palindrome"
      ],
      "session_length": "long",
      "text": "Sara: Hi, Eva! How are you doing today?\n\nEva: Good afternoon, Sara! I'm doing well, thanks. How about you?\n\nSara: I'm great! I wanted to catch up and discuss something important today\u2014building a culture of innovation and creativity within our team. It's a key aspect of any successful software engineering group, and I think it's time we dive into this topic.\n\nEva: Absolutely! I'm all for fostering creativity and innovation. It's what drew me to TECHNO in the first place. I believe a dynamic and experimental environment is crucial for both personal and professional growth.\n\nSara: Fantastic! I'm glad we're on the same page. So, the first pillar of this culture is idea-sharing. We want to create an environment where everyone feels comfortable sharing their ideas, no matter how small or seemingly insignificant. Often, the most brilliant innovations stem from a simple thought or question.\n\nEva: Idea-sharing creates a sense of collaboration and engagement, doesn't it? It encourages a collective ownership of our projects and fosters a community feel. I think it's important to have avenues where we can share our thoughts freely, whether it's during meetings, through internal forums, or even casual conversations over coffee.\n\nSara: Exactly! And it's our role as mentors and experienced engineers to ensure that these ideas are met with openness and encouragement. Sometimes, all it takes is a little spark to ignite a brilliant solution or a fresh perspective. We should always be on the lookout for those moments and create an environment that nurtures them.\n\nEva: That's a great point. Mentorship plays a vital role in this culture, too. I remember when I first started, having a more experienced engineer guide me through the intricacies of a project made a huge difference in my confidence and creativity.\n\nSara: Indeed! Mentorship is a two-way street as well. While we guide and nurture new talent, we also learn from their fresh eyes and unique backgrounds. It keeps us all growing and evolving. Now, the other crucial aspect is experimentation. We want to encourage a 'test and learn' mentality, where trying out new ideas and technologies is the norm.\n\nEva: Oh, I love the sound of that! Experimentation is where the magic happens. It gives us the freedom to explore, tinker, and sometimes fail, which is all part of the process. I think providing the resources and support for engineers to experiment is essential. Whether it's dedicated R&D time or access to the latest tools and frameworks, we should empower everyone to take calculated risks.\n\nSara: Well said, Eva! Failure is often seen as a negative, but in a culture of innovation, it becomes a learning opportunity. We can frame it as feedback, something that guides us toward a better solution. And when we do succeed, it's a huge boost to morale and inspires others to take those leaps of faith, too.\n\nEva: Absolutely! It's about creating a safe space to try, fail, learn, and ultimately succeed. I think a key part of this is also documenting and sharing our experiments, whether they're successful or not. It prevents others from repeating the same pitfalls and encourages a continuous learning cycle.\n\nSara: Brilliant insight! Documentation is indeed key to institutionalizing knowledge and ensuring that our learnings are not lost. It also creates a knowledge base that others can build upon, further fostering that collaborative spirit.\n\nEva: Exactly! And it aligns with our idea-sharing culture, too. So, what are some concrete steps we can take to further encourage this culture of innovation and creativity within our team?\n\nSara: Well, a few things come to mind. First, let's ensure that our team meetings always include a dedicated slot for new ideas and experimentation. This could be a quick round-robin where everyone shares something they've been thinking about or working on.\n\nEva: That's a great idea! It gives everyone a voice and makes sure that even the quieter team members have a platform. I think we should also consider creating an internal blog or forum where we can document and discuss our experiments and learnings. This way, even those not directly involved can benefit and contribute.\n\nSara: Fantastic suggestion! It adds a layer of structure to our knowledge-sharing and creates a lasting resource. Another idea is to organize periodic hackathons or code sprints focused on innovation. These events can be themed around a specific challenge or new technology, encouraging everyone to step outside their comfort zones.\n\nEva: Ooh, I love hackathons! They're such a fun way to dive into new territories and collaborate with colleagues we might not work with daily. And the sense of achievement afterward is always immense, whether we succeed or learn valuable lessons.\n\nSara: Absolutely! They're a brilliant way to inject energy and excitement into our innovation culture. And lastly, let's not forget the power of recognition and celebration. When innovative ideas or experiments bear fruit, let's make sure we shine a spotlight on them. It could be through internal newsletters, awards, or even a simple shout-out during our team meetings.\n\nEva: Recognition goes a long way, doesn't it? It not only makes the individual or team feel valued but also inspires others to strive for the same. I think it's a wonderful way to keep the culture of innovation thriving and visible within TECHNO.\n\nSara: Absolutely! So, those are a few ideas to get us started. I'm excited to see where this journey takes us and how we can further nurture creativity and innovation within our team.\n\nEva: Me too, Sara! I feel energized and ready to take on new challenges. Thank you for always guiding and inspiring me. I think our team is in good hands, and together, we'll create an innovative and collaborative force to be reckoned with!\n\nSara: You're very welcome, Eva. It's been a pleasure mentoring and working with you. I have no doubt that with your ambition and drive, coupled with our collective efforts, we'll achieve amazing things. Here's to a future filled with brilliant ideas and groundbreaking innovations!"
    }
  ]
}